a2y_touchui.cp312-win_amd64.pyd
a2y_touchui-1.4.dist-info/LICENSE
a2y_touchui-1.4.dist-info/METADATA
a2y_touchui-1.4.dist-info/WHEEL
a2y_touchui-1.4.dist-info/top_level.txt
a2y_touchui-1.4.dist-info/RECORD
